ht_pricing_module/__init__.py
ht_pricing_module/simple_pricer_engine.py
ht_pricing_module/api_and_utils/__init__.py
ht_pricing_module/api_and_utils/api.py
ht_pricing_module/api_and_utils/packages.py
ht_pricing_module/api_and_utils/utils.py
ht_pricing_module/api_and_utils/protos/__init__.py
ht_pricing_module/api_and_utils/protos/pricer.proto
ht_pricing_module/api_and_utils/protos/google/api/annotations.proto
ht_pricing_module/api_and_utils/protos/google/api/http.proto
ht_pricing_module/api_and_utils/protos/google/protobuf/any.proto
ht_pricing_module/api_and_utils/protos/google/protobuf/descriptor.proto
ht_pricing_module/finite_difference_engine/__init__.py
ht_pricing_module/finite_difference_engine/one_asset_crank_nicolson_american.py
ht_pricing_module/finite_difference_engine/one_asset_crank_nicolson_european.py
ht_pricing_module/finite_difference_engine/one_asset_explicit_european.py
ht_pricing_module/finite_difference_engine/one_asset_fd_generator.py
ht_pricing_module/finite_difference_engine/one_asset_fd_generator_parisian_snowball.py
ht_pricing_module/finite_difference_engine/one_asset_fd_generator_snowball.py
ht_pricing_module/finite_difference_engine/one_asset_implicit_european.py
ht_pricing_module/finite_difference_engine/two_asset_fd_generator_snowball.py
ht_pricing_module/monte_carlo_engine/__init__.py
ht_pricing_module/monte_carlo_engine/mc_path_generator.py
ht_pricing_module/multi_asset_pricing_module/__init__.py
ht_pricing_module/multi_asset_pricing_module/multi_asset_option_base.py
ht_pricing_module/multi_asset_pricing_module/basket/__init__.py
ht_pricing_module/multi_asset_pricing_module/basket/two_asset_basket_as.py
ht_pricing_module/multi_asset_pricing_module/quotient/__init__.py
ht_pricing_module/multi_asset_pricing_module/quotient/two_asset_quotient_as.py
ht_pricing_module/multi_asset_pricing_module/rainbow/__init__.py
ht_pricing_module/multi_asset_pricing_module/rainbow/three_asset_best_of_as.py
ht_pricing_module-0.5.1.dist-info/METADATA
ht_pricing_module-0.5.1.dist-info/WHEEL
ht_pricing_module-0.5.1.dist-info/top_level.txt
ht_pricing_module-0.5.1.dist-info/RECORD
