Metadata-Version: 2.1
Name: ht_pricing_module
Version: 0.5.1
Summary: huatai option pricing module
Home-page: http://10.17.75.129:9002/wangjun/ht_pricing_server/-/tree/main/ht_pricing_module
Author: wangjun
Author-email: wangjun@htgwfzb.com
Platform: any
Requires-Dist: numpy
Requires-Dist: scipy
Requires-Dist: pandas
Requires-Dist: grpcio ==1.38.0
Requires-Dist: grpcio-status ==1.38.0
Requires-Dist: grpcio-tools ==1.38.0
Requires-Dist: protobuf ==3.17.3
